virtool_workflow/__init__.py
virtool_workflow/analysis/__init__.py
virtool_workflow/analysis/fastqc.py
virtool_workflow/analysis/skewer.py
virtool_workflow/analysis/trimming.py
virtool_workflow/analysis/utils.py
virtool_workflow/api/__init__.py
virtool_workflow/api/acquire.py
virtool_workflow/api/client.py
virtool_workflow/api/utils.py
virtool_workflow/cli.py
virtool_workflow/data/__init__.py
virtool_workflow/data/analyses.py
virtool_workflow/data/hmms.py
virtool_workflow/data/indexes.py
virtool_workflow/data/jobs.py
virtool_workflow/data/ml.py
virtool_workflow/data/samples.py
virtool_workflow/data/subtractions.py
virtool_workflow/data/uploads.py
virtool_workflow/decorators.py
virtool_workflow/errors.py
virtool_workflow/files.py
virtool_workflow/hooks.py
virtool_workflow/pytest_plugin/__init__.py
virtool_workflow/pytest_plugin/data.py
virtool_workflow/pytest_plugin/utils.py
virtool_workflow/runtime/__init__.py
virtool_workflow/runtime/config.py
virtool_workflow/runtime/discover.py
virtool_workflow/runtime/events.py
virtool_workflow/runtime/hook.py
virtool_workflow/runtime/path.py
virtool_workflow/runtime/ping.py
virtool_workflow/runtime/redis.py
virtool_workflow/runtime/run.py
virtool_workflow/runtime/run_subprocess.py
virtool_workflow/runtime/sentry.py
virtool_workflow/utils.py
virtool_workflow/workflow.py
virtool_workflow-7.2.3.dist-info/LICENSE
virtool_workflow-7.2.3.dist-info/METADATA
virtool_workflow-7.2.3.dist-info/WHEEL
virtool_workflow-7.2.3.dist-info/entry_points.txt
virtool_workflow-7.2.3.dist-info/RECORD
