Metadata-Version: 2.3
Name: virtool-workflow
Version: 7.2.3
Summary: A framework for developing bioinformatics workflows for Virtool.
License: MIT
Author: Ian Boyes
Maintainer: Ian Boyes
Requires-Python: >=3.12.3,<3.13.0
Classifier: License :: OSI Approved :: MIT License
Classifier: Programming Language :: Python :: 3
Requires-Dist: aiofiles (>=24.1.0,<25.0.0)
Requires-Dist: aiohttp (>=3.12.15,<4.0.0)
Requires-Dist: biopython (>=1.81,<2.0)
Requires-Dist: click (>=8.2.1,<9.0.0)
Requires-Dist: orjson (>=3.11.1,<4.0.0)
Requires-Dist: pydantic-factories (>=1.17.3,<2.0.0)
Requires-Dist: pyfixtures (>=1.0.0,<2.0.0)
Requires-Dist: sentry-sdk (>=2.34.1,<3.0.0)
Requires-Dist: structlog-sentry (>=2.2.1,<3.0.0)
Requires-Dist: virtool (>=31.9.0,<32.0.0)
